{
  "parent": "minecraft:recipes/root",
  "criteria": {
    "has_prism_solution": {
      "conditions": {
        "items": [
          {
            "items": [
              "terramity:prism_solution_bucket"
            ]
          }
        ]
      },
      "trigger": "minecraft:inventory_changed"
    },
    "has_the_recipe": {
      "conditions": {
        "recipe": "brutality:carton_of_prism_solution_milk"
      },
      "trigger": "minecraft:recipe_unlocked"
    }
  },
  "requirements": [
    [
      "has_prism_solution",
      "has_the_recipe"
    ]
  ],
  "rewards": {
    "recipes": [
      "brutality:carton_of_prism_solution_milk"
    ]
  },
  "sends_telemetry_event": false
}