{
  "parent": "minecraft:recipes/root",
  "criteria": {
    "has_battery": {
      "conditions": {
        "items": [
          {
            "items": [
              "terramity:battery"
            ]
          }
        ]
      },
      "trigger": "minecraft:inventory_changed"
    },
    "has_the_recipe": {
      "conditions": {
        "recipe": "brutality:upper_hvac"
      },
      "trigger": "minecraft:recipe_unlocked"
    }
  },
  "requirements": [
    [
      "has_battery",
      "has_the_recipe"
    ]
  ],
  "rewards": {
    "recipes": [
      "brutality:upper_hvac"
    ]
  },
  "sends_telemetry_event": false
}