{
	"format_version": "1.12.0",
	"minecraft:geometry": [
		{
			"description": {
				"identifier": "geometry.thrown_cabbage",
				"texture_width": 64,
				"texture_height": 64,
				"visible_bounds_width": 2,
				"visible_bounds_height": 2.5,
				"visible_bounds_offset": [0, 0.75, 0]
			},
			"bones": [
				{
					"name": "bone5",
					"pivot": [0, 2, 0],
					"cubes": [
						{
							"origin": [-4, -2, -4],
							"size": [8, 8, 8],
							"uv": {
								"north": {"uv": [14, 0], "uv_size": [8, 8]},
								"east": {"uv": [14, 8], "uv_size": [8, 8]},
								"south": {"uv": [14, 16], "uv_size": [8, 8]},
								"west": {"uv": [22, 0], "uv_size": [8, 8]},
								"up": {"uv": [22, 8], "uv_size": [8, 8]},
								"down": {"uv": [22, 24], "uv_size": [8, -8]}
							}
						},
						{
							"origin": [-7, -2, -7],
							"size": [14, 0, 14],
							"inflate": 0.01,
							"uv": {
								"up": {"uv": [0, 0], "uv_size": [14, 14]},
								"down": {"uv": [0, 28], "uv_size": [14, -14]}
							}
						}
					]
				},
				{
					"name": "bone",
					"parent": "bone5",
					"pivot": [0, -2, 0],
					"cubes": [
						{
							"origin": [-4, -2, -4],
							"size": [0, 6, 8],
							"inflate": 0.01,
							"pivot": [-4, -2, 0],
							"rotation": [0, 0, -22.5],
							"uv": {
								"east": {"uv": [14, 24], "uv_size": [8, 6]},
								"west": {"uv": [14, 24], "uv_size": [8, 6]}
							}
						},
						{
							"origin": [-4, -2, -4],
							"size": [0, 4, 8],
							"inflate": 0.01,
							"pivot": [-4, -2, 0],
							"rotation": [0, 0, -67.5],
							"uv": {
								"east": {"uv": [22, 28], "uv_size": [8, 4]},
								"west": {"uv": [22, 24], "uv_size": [8, 4]}
							}
						}
					]
				},
				{
					"name": "bone2",
					"parent": "bone5",
					"pivot": [0, -2, 0],
					"rotation": [0, -90, 0],
					"cubes": [
						{
							"origin": [-4, -2, -4],
							"size": [0, 6, 8],
							"inflate": 0.01,
							"pivot": [-4, -2, 0],
							"rotation": [0, 0, -22.5],
							"uv": {
								"east": {"uv": [14, 24], "uv_size": [8, 6]},
								"west": {"uv": [14, 24], "uv_size": [8, 6]}
							}
						},
						{
							"origin": [-4, -2, -4],
							"size": [0, 4, 8],
							"inflate": 0.01,
							"pivot": [-4, -2, 0],
							"rotation": [0, 0, -67.5],
							"uv": {
								"east": {"uv": [22, 28], "uv_size": [8, 4]},
								"west": {"uv": [22, 24], "uv_size": [8, 4]}
							}
						}
					]
				},
				{
					"name": "bone3",
					"parent": "bone5",
					"pivot": [0, -2, 0],
					"rotation": [0, 180, 0],
					"cubes": [
						{
							"origin": [-4, -2, -4],
							"size": [0, 6, 8],
							"inflate": 0.01,
							"pivot": [-4, -2, 0],
							"rotation": [0, 0, -22.5],
							"uv": {
								"east": {"uv": [14, 24], "uv_size": [8, 6]},
								"west": {"uv": [14, 24], "uv_size": [8, 6]}
							}
						},
						{
							"origin": [-4, -2, -4],
							"size": [0, 4, 8],
							"inflate": 0.01,
							"pivot": [-4, -2, 0],
							"rotation": [0, 0, -67.5],
							"uv": {
								"east": {"uv": [22, 28], "uv_size": [8, 4]},
								"west": {"uv": [22, 24], "uv_size": [8, 4]}
							}
						}
					]
				},
				{
					"name": "bone4",
					"parent": "bone5",
					"pivot": [0, -2, 0],
					"rotation": [0, 90, 0],
					"cubes": [
						{
							"origin": [-4, -2, -4],
							"size": [0, 6, 8],
							"inflate": 0.01,
							"pivot": [-4, -2, 0],
							"rotation": [0, 0, -22.5],
							"uv": {
								"east": {"uv": [14, 24], "uv_size": [8, 6]},
								"west": {"uv": [14, 24], "uv_size": [8, 6]}
							}
						},
						{
							"origin": [-4, -2, -4],
							"size": [0, 4, 8],
							"inflate": 0.01,
							"pivot": [-4, -2, 0],
							"rotation": [0, 0, -67.5],
							"uv": {
								"east": {"uv": [22, 28], "uv_size": [8, 4]},
								"west": {"uv": [22, 24], "uv_size": [8, 4]}
							}
						}
					]
				}
			]
		}
	]
}